Workbook

Sheet NAV Dashboard
A1: GAM FUNDS - NAV DASHBOARD
A2: Report Date: | B2: =TODAY() -> 46160
A4: STABLE GROWTH FUND (SGF) | D4: URBAN SKY FUND (USF)
A5: NAV per Unit (MNT) | B5: ='SGF NAV Calc'!B24 -> 2736.0002 | D5: NAV per Unit (MNT) | E5: ='USF NAV Calc'!B23 -> 321333.33
A6: Total Net Assets (MNT) | B6: ='SGF NAV Calc'!B22 -> 2736000235000 | D6: Total Net Assets (MNT) | E6: ='USF NAV Calc'!B21 -> 48200000000
A7: Outstanding Units | B7: ='SGF NAV Calc'!B23 -> 1000000000 | D7: Outstanding Units | E7: ='USF NAV Calc'!B22 -> 150000
A8: FRC Utilization % | B8: ='SGF NAV Calc'!B27 -> 1.8240002e+14 | D8: FRC Utilization % | E8: ='USF NAV Calc'!B25 -> 2410000000000
A9: FRC Raise Limit (MNT) | B9: ='SGF NAV Calc'!B26 -> 0.015 | D9: FRC Raise Limit (MNT) | E9: ='USF NAV Calc'!B24 -> 0.02
A11: Green values = cross-sheet links from NAV Calc tabs. Update asset values in SGF NAV Calc / USF NAV Calc tabs, then this dashboard refreshes automatically.

Sheet SGF NAV Calc
A1: STABLE GROWTH FUND - NAV CALCULATION
A2: Valuation Date: | B2: =TODAY() -> 46160
A4: TOTAL ASSETS | B4: MNT
A5: Listed Equities (Market Value) | B5: 2130000000000 | C5: Source: Portfolio_Holdings.xlsx > SGF Holdings
A6: Government Bonds (Market Value) | B6: 505000000000
A7: Corporate Bonds (Market Value) | B7: 100500000000
A8: ETF / Fund Units (Market Value) | B8: 235000
A9: Cash & Cash Equivalents | B9: 500000000
A10: Accrued Income | B10: 0
A11: Other Assets | B11: 0
A12: GROSS TOTAL ASSETS | B12: =SUM(B5:B11) -> 2736000235000
A14: TOTAL LIABILITIES | B14: MNT
A15: Management Fee Payable | B15: 0
A16: Performance Fee Payable | B16: 0
A17: Redemptions Payable | B17: 0
A18: Other Payables | B18: 0
A19: TOTAL LIABILITIES | B19: =SUM(B15:B18) -> 0
A21: NET ASSET VALUE (NAV)
A22: Total Net Assets (MNT) | B22: =B12-B19 -> 2736000235000 | C22: =Gross Assets minus Liabilities -> #NAME?
A23: Outstanding Units | B23: =Assumptions!B5 -> 1000000000
A24: NAV per Unit (MNT) | B24: =IF(B23=0,0,B22/B23) -> 2736.0002 | C24: KEY OUTPUT - update to client statements
A25: Total Subscriptions YTD (MNT)
A26: FRC Raise Limit (MNT) | B26: =Assumptions!B7 -> 0.015
A27: FRC Utilization % | B27: =IF(B26=0,0,B22/B26) -> 1.8240002e+14 | C27: Must be <= 100%. Flag if approaching limit.

Sheet USF NAV Calc
A1: URBAN SKY FUND - NAV CALCULATION
A2: Valuation Date: | B2: =TODAY() -> 46160
A4: TOTAL ASSETS | B4: MNT
A5: Real Estate Projects (Appraised Value) | B5: 22000000000 | C5: Source: Portfolio_Holdings.xlsx > USF Holdings (appraisal / audited values)
A6: SPV Preferred Shares (Fair Value) | B6: 15500000000
A7: Project Bonds (Amortised Cost) | B7: 10200000000
A8: Cash & Cash Equivalents | B8: 500000000
A9: Accrued Income | B9: 0
A10: Other Assets | B10: 0
A11: GROSS TOTAL ASSETS | B11: =SUM(B5:B10) -> 48200000000
A13: TOTAL LIABILITIES | B13: MNT
A14: Management Fee Payable | B14: 0
A15: Performance Fee Payable | B15: 0
A16: Redemptions Payable | B16: 0
A17: Other Payables | B17: 0
A18: TOTAL LIABILITIES | B18: =SUM(B14:B17) -> 0
A20: NET ASSET VALUE (NAV)
A21: Total Net Assets (MNT) | B21: =B11-B18 -> 48200000000
A22: Outstanding Units | B22: =Assumptions!C5 -> 150000
A23: NAV per Unit (MNT) | B23: =IF(B22=0,0,B21/B22) -> 321333.33 | C23: KEY OUTPUT - update to client statements
A24: FRC Raise Limit (MNT) | B24: =Assumptions!C7 -> 0.02
A25: FRC Utilization % | B25: =IF(B24=0,0,B21/B24) -> 2410000000000

Sheet Assumptions
A1: FUND ASSUMPTIONS (Link to SGF_URF_Fund_Config.xlsx for live data)
A2: Parameter | B2: SGF | C2: USF | D2: Notes
A3: Fund Name | B3: Stable Growth Fund | C3: Urban Sky Fund
A4: Unit Price (MNT) | B4: 100 | C4: 1000000 | D4: Per unit face value
A5: Outstanding Units | B5: 1000000000 | C5: 150000 | D5: Update after each subscription/redemption
A6: FRC Raise Limit (MNT) | B6: 100000000000 | C6: 150000000000 | D6: Authorized maximum
A7: Management Fee (%/yr) | B7: 0.015 | C7: 0.02 | D7: Annual management fee rate
A8: Performance Fee (%) | B8: 0.2 | C8: 0.2 | D8: 20% of gains above high-water mark
A9: Valuation Frequency | B9: Daily | C9: Monthly
A10: Base Currency | B10: MNT | C10: MNT
