Workbook

Sheet SGF Holdings
A1: STABLE GROWTH FUND - PORTFOLIO HOLDINGS
A2: Asset ID | B2: Asset Name | C2: Asset Type | D2: Ticker / ISIN | E2: Country | F2: Sector / Rating | G2: Currency | H2: Quantity | I2: Cost Price | J2: Book Value (MNT) | K2: Current Price | L2: Market Value (MNT) | M2: Unrealized P&L (MNT) | N2: Weight % | O2: Notes
A3: SGF-EQ-001 | B3: Mongolian Mining Corp | C3: Listed Equity | D3: MMC | E3: Mongolia | F3: Basic Materials / - | G3: MNT | H3: 100000 | I3: 5500 | J3: =H3*I3 -> 550000000 | L3: =H3*K3 -> 0 | M3: =L3-J3 -> -550000000 | N3: =L3/SUM(L3:L7) -> #DIV/0!
A4: SGF-EQ-002 | B4: Trade & Development Bank | C4: Listed Equity | D4: TDB | E4: Mongolia | F4: Financials / - | G4: MNT | H4: 50000 | I4: 10200 | J4: =H4*I4 -> 510000000 | L4: =H4*K4 -> 0 | M4: =L4-J4 -> -510000000 | N4: =L4/SUM(L3:L7) -> #DIV/0!
A5: SGF-BD-001 | B5: MNT Govt Bond 2026 | C5: Government Bond | D5: MN-GOV-2026 | E5: Mongolia | F5: Government / AA | G5: MNT | H5: 500000000 | I5: 1000 | J5: =H5*I5 -> 500000000000 | L5: =H5*K5 -> 0 | M5: =L5-J5 -> -500000000000 | N5: =L5/SUM(L3:L7) -> #DIV/0!
A6: SGF-BD-002 | B6: Mongolian Coal Corp Bond | C6: Corporate Bond | D6: MCC-B-2025 | E6: Mongolia | F6: Energy / BBB | G6: MNT | H6: 100000000 | I6: 1000 | J6: =H6*I6 -> 100000000000 | L6: =H6*K6 -> 0 | M6: =L6-J6 -> -100000000000 | N6: =L6/SUM(L3:L7) -> #DIV/0!
A7: SGF-ET-001 | B7: iShares MSCI EM ETF | C7: ETF | D7: EEM | E7: USA | F7: Emerging Markets / - | G7: USD | H7: 5000 | I7: 45 | J7: =H7*I7 -> 225000 | L7: =H7*K7 -> 0 | M7: =L7-J7 -> -225000 | N7: =L7/SUM(L3:L7) -> #DIV/0!
A8: TOTAL | J8: =SUM(J3:J7) -> 601060225000 | L8: =SUM(L3:L7) -> 0 | M8: =SUM(M3:M7) -> -601060225000

Sheet USF Holdings
A1: URBAN SKY FUND - PORTFOLIO HOLDINGS
A2: Asset ID | B2: Project Name | C2: Asset Type | D2: Project Code | E2: Currency | F2: Investment Amount (MNT) | G2: Current Valuation (MNT) | H2: Unrealized P&L (MNT) | I2: Weight % | J2: Location | K2: Development Stage | L2: Expected Completion | M2: Notes
A3: USF-RE-001 | B3: Sky Tower Residential | C3: Real Estate Direct | D3: SKY-001 | E3: MNT | F3: 20000000000 | G3: 22000000000 | H3: =G3-F3 -> 2000000000 | I3: =G3/SUM(G3:G5) -> 0.46121593 | J3: Ulaanbaatar, Sukhbaatar | K3: Construction | L3: 2026-06
A4: USF-SPV-001 | B4: Green City SPV | C4: SPV Preferred Shares | D4: GCS-001 | E4: MNT | F4: 15000000000 | G4: 15500000000 | H4: =G4-F4 -> 500000000 | I4: =G4/SUM(G3:G5) -> 0.32494759 | J4: Ulaanbaatar, Khan-Uul | K4: Pre-sales | L4: 2027-03
A5: USF-BD-001 | B5: Nomadic Homes Proj Bond | C5: Project Bond | D5: NH-BD-001 | E5: MNT | F5: 10000000000 | G5: 10200000000 | H5: =G5-F5 -> 200000000 | I5: =G5/SUM(G3:G5) -> 0.21383648 | J5: Darkhan | K5: Planning | L5: 2027-12
A6: TOTAL | F6: =SUM(F3:F5) -> 45000000000 | G6: =SUM(G3:G5) -> 47700000000 | H6: =SUM(H3:H5) -> 2700000000

Sheet SGF Summary
A1: SGF - ASSET CLASS BREAKDOWN
A2: Asset Class | B2: Market Value (MNT) | C2: Weight % | D2: FRC Max Weight | E2: Compliance Status
A3: Listed Equities | B3: 2130000000000 | C3: =IF(SUM('SGF Holdings'!L3:L7)=0,0,B3/SUM(B3:B7)) -> 0 | D3: 0.6 | E3: =IF(C3<=VALUE(LEFT(D3,LEN(D3)-1))/100,"OK","BREACH") -> OK
A4: Government Bonds | B4: 505000000000 | C4: =IF(SUM('SGF Holdings'!L3:L7)=0,0,B4/SUM(B3:B7)) -> 0 | D4: 0.8 | E4: =IF(C4<=VALUE(LEFT(D4,LEN(D4)-1))/100,"OK","BREACH") -> OK
A5: Corporate Bonds | B5: 100500000000 | C5: =IF(SUM('SGF Holdings'!L3:L7)=0,0,B5/SUM(B3:B7)) -> 0 | D5: 0.4 | E5: =IF(C5<=VALUE(LEFT(D5,LEN(D5)-1))/100,"OK","BREACH") -> OK
A6: ETF Units | B6: 235000 | C6: =IF(SUM('SGF Holdings'!L3:L7)=0,0,B6/SUM(B3:B7)) -> 0 | D6: 0.2 | E6: =IF(C6<=VALUE(LEFT(D6,LEN(D6)-1))/100,"OK","BREACH") -> OK
A7: Cash & Equivalents | B7: 0 | C7: =IF(SUM('SGF Holdings'!L3:L7)=0,0,B7/SUM(B3:B7)) -> 0 | D7: 0.2 | E7: =IF(C7<=VALUE(LEFT(D7,LEN(D7)-1))/100,"OK","BREACH") -> OK

Sheet USF Summary
A1: USF - ASSET CLASS BREAKDOWN
A2: Asset Type | B2: Cost Basis (MNT) | C2: Current Valuation (MNT) | D2: Weight % | E2: Development Stage
A3: Real Estate Direct | B3: 20000000000 | C3: 22000000000 | D3: =IF(SUM(C3:C5)=0,0,C3/SUM(C3:C5)) -> 0.46121593 | E3: Construction
A4: SPV Preferred Shares | B4: 15000000000 | C4: 15500000000 | D4: =IF(SUM(C3:C5)=0,0,C4/SUM(C3:C5)) -> 0.32494759 | E4: Pre-sales
A5: Project Bonds | B5: 10000000000 | C5: 10200000000 | D5: =IF(SUM(C3:C5)=0,0,C5/SUM(C3:C5)) -> 0.21383648 | E5: Planning
